mini_yahoo_finance.py
mini_yahoo_finance-0.0.7.dist-info/LICENSE
mini_yahoo_finance-0.0.7.dist-info/METADATA
mini_yahoo_finance-0.0.7.dist-info/WHEEL
mini_yahoo_finance-0.0.7.dist-info/top_level.txt
mini_yahoo_finance-0.0.7.dist-info/RECORD
