Metadata-Version: 2.1
Name: mini-yahoo-finance
Version: 0.0.7
Summary: Download and store historical stock data to a Pandas dataframe using the Yahoo! Finance API.
Home-page: https://github.com/lucaionescu/mini-yahoo-finance-api.git
Author: Luca Ionescu
Author-email: ionescu@mailbox.org
License: MIT
Keywords: yahoo finance stocks market
Platform: UNKNOWN
Requires-Dist: beautifulsoup4
Requires-Dist: pandas
Requires-Dist: requests
